[
  {
    "id": "pep1",
    "themaID": "pe-prozess",
    "frageNummer": 1,
    "titel": "Frage 1:",
    "frageText": "Beschreiben Sie die fünf Phasen des Personalentwicklungsprozesses und erläutern Sie deren Bedeutung für die betriebliche Praxis.",
    "commonFeedback": {
      "positiv": "Sehr gut! Dieser Aspekt wurde umfassend erkannt.",
      "neutral": "Dieser Begriff wurde erkannt, die Beschreibung könnte ausführlicher sein.",
      "negativ": "Dieser Begriff wurde nicht erwähnt."
    },
    "musterloesung": "Der Personalentwicklungsprozess gliedert sich in fünf aufeinanderfolgende Phasen:\n\n<strong>Bedarfsanalyse:</strong> Hier wird ermittelt, welche Qualifikationen im Unternehmen fehlen oder künftig benötigt werden. Dies geschieht durch Methoden wie Befragungen, Beobachtungen oder Dokumentenanalysen.\n\n<strong>Zielplanung:</strong> In dieser Phase werden konkrete Entwicklungsziele definiert, die sowohl auf individuelle als auch auf unternehmerische Anforderungen abgestimmt sind.\n\n<strong>Maßnahmengestaltung:</strong> Es werden geeignete Entwicklungsmaßnahmen ausgewählt, die sowohl pädagogisch sinnvoll als auch wirtschaftlich tragfähig sind.\n\n<strong>Durchführung:</strong> Die geplanten Maßnahmen werden umgesetzt – z. B. durch Schulungen, Coaching oder Training-on-the-Job.\n\n<strong>Erfolgskontrolle:</strong> Abschließend wird überprüft, ob die Maßnahmen die gewünschten Effekte erzielt haben. Dies kann durch Feedback, Tests oder Leistungsbeurteilungen erfolgen.\n\nDer strukturierte Ablauf stellt sicher, dass Personalentwicklung zielgerichtet, effizient und nachhaltig erfolgt.",
    "bewertungskriterien": [
      {
        "name": "Bedarfsanalyse",
        "keywords": [
          "die bedarfsanalyse", "bedarf ermitteln", "qualifikationen fehlen", "was gebraucht wird",
          "was mitarbeiter können oder brauchen", "was mitarbeiter können", "was mitarbeiter brauchen",
          "bedarf", "bedarfsanalyse", "ermittlung", "qualifikationen", "befragung", "beobachtung",
          "dokumentenanalyse", "ermittelt", "fähigkeiten", "benötigt", "können", "brauchen", "analyse des bedarfs", "bedarfs ermitteln"
        ],
        "phrases": [
            "bedarfsanalyse",
            "bedarf ermitteln",
            "qualifikationen fehlen",
            "was gebraucht wird",
            "was mitarbeiter können oder brauchen",
            "analyse des bedarfs",
            "personalbedarfsanalyse"
        ]
      },
      {
        "name": "Zielplanung",
        "keywords": [
          "die zielplanung", "ziele festlegen", "ziele definieren", "richtung festgelegt",
          "ziele gesetzt", "klare ziele", "ziele setzen",
          "ziel", "ziele", "zielplanung", "entwicklungsziele", "individuell", "unternehmerisch",
          "abstimmung", "lernziele", "richtung", "festgelegt", "erreicht", "definiert", "zielplanung"
        ],
        "phrases": [
            "zielplanung",
            "ziele festlegen",
            "entwicklungsziele definieren",
            "konkrete ziele",
            "zielplanung festlegen"
        ]
      },
      {
        "name": "Maßnahmengestaltung",
        "keywords": [
          "maßnahmengestaltung", "maßnahmen planen", "angebote vorbereiten", "passende angebote",
          "geplante maßnahmen", "maßnahmen zur umsetzung", "planung von angeboten", "maßnahmen zur umsetzung",
          "maßnahme", "maßnahmen", "gestaltung", "gestalten", "auswählen", "pädagogisch",
          "wirtschaftlich", "planen", "fortbildungen", "angebote", "vorbereitet", "lernmaßnahmen", "massnahmen", "maßnahmen erstellen", "maßnahmen gestalten"
        ],
        "phrases": [
            "maßnahmengestaltung",
            "maßnahmen planen",
            "entwicklungsmaßnahmen auswählen",
            "maßnahmen gestalten",
            "gestaltung von maßnahmen"
        ]
      },
      {
        "name": "Durchführung",
        "keywords": [
          "maßnahmen umsetzen", "im betrieb umgesetzt", "coaching durchführen",
          "durchführung des prozesses", "umsetzung muss begleitet werden", "tatsächliche umsetzung", "umsetzung ist teil davon",
          "durchführung", "umsetzung", "umsetzen", "schulung", "coaching", "training-on-the-job",
          "durchgeführt", "umgesetzt", "implementiert", "betrieb", "durchführen", "maßnahmen durchführen"
        ],
        "phrases": [
            "durchführung der maßnahmen",
            "maßnahmen umsetzen",
            "durchführung der entwicklung",
            "umsetzung der maßnahmen"
        ]
      },
      {
        "name": "Erfolgskontrolle",
        "keywords": [
          "erfolgskontrolle", "wirksamkeit überprüfen", "ob es was gebracht hat", "erfolg prüfen",
          "erfolg überprüfen", "abschließende kontrolle", "was es gebracht hat", "ob es funktioniert hat", "auswertung habe ich nicht genannt", "bewertung machen",
          "kontrolle", "überprüfung", "feedback", "tests", "leistungsbeurteilung",
          "erfolg erzielt", "überprüft", "wirksamkeit", "gebracht", "beurteilt", "schaut", "auswertung", "messung", "erfolg kontrollieren"
        ],
        "phrases": [
            "erfolgskontrolle",
            "wirksamkeit überprüfen",
            "erfolg überprüfen",
            "kontrolle des erfolgs",
            "überprüfung der wirksamkeit"
        ]
      }
    ]
  },
  {
    "id": "pep2",
    "themaID": "pe-prozess",
    "frageNummer": 2,
    "titel": "Frage 2:",
    "frageText": "Warum ist die Personalentwicklung ein strategisches Instrument zur Sicherung der Wettbewerbsfähigkeit?",
    "commonFeedback": {
      "positiv": "Sehr gut! Dieser Aspekt wurde umfassend erkannt.",
      "neutral": "Dieser Begriff wurde erkannt, die Beschreibung könnte ausführlicher sein.",
      "negativ": "Dieser Begriff wurde nicht erwähnt."
    },
    "musterloesung": "Personalentwicklung trägt wesentlich zur <strong>langfristigen Wettbewerbsfähigkeit eines Unternehmens</strong> bei. \n\n<strong>Bedeutung im Kontext von Fachkräftemangel & Wandel:</strong> In Zeiten des Fachkräftemangels und des raschen technologischen Wandels ist es entscheidend, Mitarbeitende kontinuierlich weiterzubilden.\n\n<strong>Vorteile für Mitarbeitende:</strong> Durch gezielte Entwicklung können Kompetenzen aufgebaut, Motivation gesteigert und die Mitarbeiterbindung erhöht werden. \n\n<strong>Nutzen für das Unternehmen:</strong> Unternehmen, die in ihre Belegschaft investieren, sichern sich nicht nur Know-how, sondern auch Innovationskraft und Anpassungsfähigkeit. \n\n<strong>Strategische Integration:</strong> Personalentwicklung ist somit kein „Nice-to-have“, sondern ein zentraler Bestandteil der Unternehmensstrategie.",
    "bewertungskriterien": [
      {
        "name": "Bedeutung im Kontext von Fachkräftemangel & Wandel",
        "keywords": [
          "fachkräftemangel", "wandel", "technologisch", "weiterbilden", "mitarbeitende"
        ],
        "phrases": [
          "fachkräftemangel technischem wandel",
          "mitarbeitende weiterbildet",
          "bildet mitarbeitende weiter",
          "raschen technologischen wandel"
        ]
      },
      {
        "name": "Vorteile für Mitarbeitende (Kompetenz, Motivation, Bindung)",
        "keywords": [
          "kompetenzen", "motivation", "mitarbeiterbindung", "aufbauen", "steigern", "erhöhen"
        ],
        "phrases": [
          "baut kompetenzen auf",
          "steigert motivation",
          "erhöht mitarbeiterbindung",
          "kompetenzen aufgebaut",
          "motivation gesteigert",
          "mitarbeiterbindung erhöht"
        ]
      },
      {
        "name": "Nutzen für das Unternehmen (Know-how, Innovation, Anpassung)",
        "keywords": [
          "know-how", "innovationskraft", "anpassungsfähigkeit", "sichern"
        ],
        "phrases": [
          "sichert know-how",
          "sichert innovation",
          "sichert anpassungsfähigkeit",
          "sichert know-how innovation anpassungsfähigkeit",
          "sichert sich know-how",
          "sichert sich innovationskraft",
          "sichert sich anpassungsfähigkeit"
        ]
      },
      {
        "name": "Strategische Bedeutung / Integration in die Unternehmensstrategie",
        "keywords": [
          "strategisch", "instrument", "unternehmensstrategie", "wettbewerbsfähigkeit", "zentral"
        ],
        "phrases": [
          "strategisches instrument",
          "strategisches instrument der unternehmensstrategie",
          "unternehmensstrategie",
          "langfristigen wettbewerbsfähigkeit"
        ]
      }
    ]
  }
]
